kcolorconverter/__init__.py
kcolorconverter/constants.py
kcolorconverter/warnings.py
kcolorconverter/conversion/__init__.py
kcolorconverter/conversion/converter.py
kcolorconverter/conversion/metaclass.py
kcolorconverter-0.0.2.dist-info/LICENSE
kcolorconverter-0.0.2.dist-info/METADATA
kcolorconverter-0.0.2.dist-info/WHEEL
kcolorconverter-0.0.2.dist-info/top_level.txt
kcolorconverter-0.0.2.dist-info/RECORD
